segutils/Visualizer.py
segutils/__init__.py
segutils/graphutils.py
segutils/imutils.py
segutils/visutils.py
segutils-0.0.6.dist-info/LICENSE
segutils-0.0.6.dist-info/METADATA
segutils-0.0.6.dist-info/WHEEL
segutils-0.0.6.dist-info/top_level.txt
segutils-0.0.6.dist-info/RECORD
