Metadata-Version: 2.1
Name: segutils
Version: 0.0.6
Summary: Common utilities for image processing, segmentation, and detection
Home-page: https://github.com/tacos-galore/segutils
Author: Guy Azran
Author-email: guyazran@gmail.com
License: UNKNOWN
Platform: UNKNOWN
Classifier: Programming Language :: Python :: 3.7
Classifier: License :: OSI Approved :: GNU General Public License v3 (GPLv3)
Requires-Dist: mahotas
Requires-Dist: matplotlib
Requires-Dist: numpy
Requires-Dist: scikit-learn
